merge_conf/__init__.py
merge_conf/argparse.py
merge_conf/base.py
merge_conf/configparser.py
merge_conf/dotenv.py
merge_conf/json.py
merge_conf/module.py
merge_conf/osenv.py
merge_conf/toml.py
merge_conf/yaml.py
multiconf/__init__.py
merge_conf-0.9.0.dist-info/LICENSE
merge_conf-0.9.0.dist-info/METADATA
merge_conf-0.9.0.dist-info/WHEEL
merge_conf-0.9.0.dist-info/top_level.txt
merge_conf-0.9.0.dist-info/RECORD
