Metadata-Version: 2.1
Name: merge-conf
Version: 0.9.0
Summary: Combine multiple configuration sources to a single configuration object.
Home-page: https://github.com/carstencodes/merge-conf
Author: Carsten Igel
Author-email: cig@bite-that-bit.de
License: BSD-3-Clause
Keywords: configuration,environment,dotenv,arguments,development
Platform: UNKNOWN
Classifier: Development Status :: 4 - Beta
Classifier: Intended Audience :: Developers
Classifier: License :: OSI Approved :: BSD License
Classifier: Operating System :: OS Independent
Classifier: Programming Language :: Python :: 3.7
Classifier: Programming Language :: Python :: 3.8
Classifier: Programming Language :: Python :: 3.9
Classifier: Topic :: Software Development :: Libraries :: Python Modules
Classifier: Topic :: System
Classifier: Typing :: Typed
Requires-Python: >=3.7, < 4
Requires-Dist: xdg
Provides-Extra: dotenv
Requires-Dist: python-dotenv ; extra == 'dotenv'
Provides-Extra: toml
Requires-Dist: toml ; extra == 'toml'
Provides-Extra: yaml
Requires-Dist: pyyaml ; extra == 'yaml'
